pipeline_dp/__init__.py
pipeline_dp/aggregate_params.py
pipeline_dp/budget_accounting.py
pipeline_dp/combiners.py
pipeline_dp/contribution_bounders.py
pipeline_dp/data_extractors.py
pipeline_dp/dataframes.py
pipeline_dp/dp_computations.py
pipeline_dp/dp_engine.py
pipeline_dp/input_validators.py
pipeline_dp/partition_selection.py
pipeline_dp/pipeline_backend.py
pipeline_dp/pipeline_functions.py
pipeline_dp/private_beam.py
pipeline_dp/private_contribution_bounds.py
pipeline_dp/private_spark.py
pipeline_dp/report_generator.py
pipeline_dp/sampling_utils.py
pipeline_dp/dataset_histograms/computing_histograms.py
pipeline_dp/dataset_histograms/histogram_error_estimator.py
pipeline_dp/dataset_histograms/histograms.py
pipeline_dp-0.2.1.dist-info/LICENSE
pipeline_dp-0.2.1.dist-info/METADATA
pipeline_dp-0.2.1.dist-info/WHEEL
pipeline_dp-0.2.1.dist-info/top_level.txt
pipeline_dp-0.2.1.dist-info/RECORD
