Metadata-Version: 2.1
Name: pipeline-dp
Version: 0.2.1
Summary: Framework for applying differential privacy to large datasets using batch processing systems
Home-page: https://github.com/OpenMined/PipelineDP/
Author: Chinmay Shah
Author-email: chinmayshah3899@gmail.com
Maintainer: Vadym Doroshenko
Maintainer-email: dvadym@google.com
License: Apache-2.0
Platform: UNKNOWN
Requires-Python: >=3.8,<3.12
License-File: LICENSE
Requires-Dist: numpy (<2.0.0,>=1.20.1)
Requires-Dist: python-dp (>=1.1.5rc4)
Requires-Dist: scipy (<2.0.0,>=1.7.3)
